configs_generator/__init__.py
configs_generator/__main__.py
configs_generator/confGen.py
configs_generator-0.0.7.dist-info/LICENSE
configs_generator-0.0.7.dist-info/METADATA
configs_generator-0.0.7.dist-info/WHEEL
configs_generator-0.0.7.dist-info/top_level.txt
configs_generator-0.0.7.dist-info/RECORD
