Metadata-Version: 2.1
Name: configs-generator
Version: 0.0.7
Summary: Configuration generation from Excel Facts File
Home-page: https://github.com/aliasgar1978/configs_generator
Author: ALIASGAR - ALI
Author-email: aholo2000@gmail.com
Classifier: Programming Language :: Python :: 3
Classifier: License :: OSI Approved :: MIT License
Classifier: Operating System :: OS Independent
Requires-Python: >=3.7
License-File: LICENSE
Requires-Dist: pandas
Requires-Dist: xlrd
Requires-Dist: nettoolkit
